[
  {
    "id": "borodinsky",
    "name": "Бородинский",
    "anchor": [
      37.556,
      55.741
    ]
  },
  {
    "id": "krymsky",
    "name": "Крымский",
    "anchor": [
      37.617,
      55.731
    ]
  },
  {
    "id": "kamenny",
    "name": "Каменный",
    "anchor": [
      37.622,
      55.745
    ]
  },
  {
    "id": "moskvoretsky",
    "name": "Москворецкий",
    "anchor": [
      37.63,
      55.749
    ]
  },
  {
    "id": "novospassky",
    "name": "Новоспасский",
    "anchor": [
      37.661,
      55.733
    ]
  },
  {
    "id": "nagatinsky",
    "name": "Нагатинский",
    "anchor": [
      37.665,
      55.685
    ]
  },
  {
    "id": "andreevsky",
    "name": "Андреевский",
    "anchor": [
      37.58,
      55.703
    ]
  }
]
